xml2dcm/__init__.py
xml2dcm/ecg_dcm_metadata.py
xml2dcm/main.py
xml2dcm/utils.py
xml2dcm_ecg-1.1.10.dist-info/METADATA
xml2dcm_ecg-1.1.10.dist-info/WHEEL
xml2dcm_ecg-1.1.10.dist-info/entry_points.txt
xml2dcm_ecg-1.1.10.dist-info/top_level.txt
xml2dcm_ecg-1.1.10.dist-info/RECORD
