Metadata-Version: 2.4
Name: XML2DCM-ECG
Version: 1.1.10
Summary: Python-based solution for converting ECG data from XML format to the DICOM(Digital Imaging and Communications in Medicine) format
Author-email: eunbyul <eunbyul616@gmail.com>
License-Expression: MIT
Requires-Python: >=3.10
Requires-Dist: numpy
Requires-Dist: tqdm
Requires-Dist: pydicom==2.4.4
